huey-stubs/__init__.pyi
huey-stubs/api.pyi
huey-stubs/bin/__init__.pyi
huey-stubs/bin/huey_consumer.pyi
huey-stubs/constants.pyi
huey-stubs/consumer.pyi
huey-stubs/consumer_options.pyi
huey-stubs/contrib/__init__.pyi
huey-stubs/contrib/djhuey/__init__.pyi
huey-stubs/contrib/kyototycoon.pyi
huey-stubs/contrib/mini.pyi
huey-stubs/contrib/sql_huey.pyi
huey-stubs/exceptions.pyi
huey-stubs/registry.pyi
huey-stubs/serializer.pyi
huey-stubs/signals.pyi
huey-stubs/storage.pyi
huey-stubs/utils.pyi
huey_stubs-0.0.2.dist-info/LICENSE
huey_stubs-0.0.2.dist-info/WHEEL
huey_stubs-0.0.2.dist-info/METADATA
huey_stubs-0.0.2.dist-info/RECORD
